Xray/ListenerV2.py
Xray/__init__.py
Xray/config.py
Xray/xray.py
robotframework_xray-5.2.0.dist-info/METADATA
robotframework_xray-5.2.0.dist-info/WHEEL
robotframework_xray-5.2.0.dist-info/top_level.txt
robotframework_xray-5.2.0.dist-info/RECORD
