Metadata-Version: 2.1
Name: robotframework-xray
Version: 5.2.0
Home-page: https://github.com/kriffx/robotframework-xray
Author: Cleverson Sampaio
Author-email: cleverson@sampaio.dev.br
Requires-Dist: robotframework >=6.1.1
Requires-Dist: robotframework-seleniumlibrary >=6.5.0
Requires-Dist: beautifulsoup4 >=4.12.3
Requires-Dist: requests >=2.32.3
Requires-Dist: load-dotenv >=0.1.0
Requires-Dist: pyscreenrec >=0.4
Requires-Dist: python-dateutil >=2.9.0.post0
